ntfyr/__init__.py
ntfyr/__main__.py
ntfyr/_common.py
ntfyr/config.py
ntfyr/errors.py
ntfyr/ntfyr.py
tests/__init__.py
tests/conftest.py
tests/test_config.py
tests/test_end_to_end.py
tests/test_main_args.py
tests/test_ntfyr.py
ntfyr-0.3.1.dist-info/LICENSE
ntfyr-0.3.1.dist-info/METADATA
ntfyr-0.3.1.dist-info/WHEEL
ntfyr-0.3.1.dist-info/entry_points.txt
ntfyr-0.3.1.dist-info/top_level.txt
ntfyr-0.3.1.dist-info/RECORD
